{"id": "ch36_2025_spain", "number": 36, "title": "スペイン (2025)", "title_en": "Spain 2025", "category": "UPDATE_2025", "icon": "✨", "description": "2025年度 J.S.A. 教本アップデート", "source_pages": [], "pages": [{"page": 1, "text": "D.O.P（. D.O.Ca./D.O./V.P./V.C.）一覧表\nスペイン （2024年6月現在）\n＊ヨーロッパ連合（eAmbrosia登録）、MAPA（スペイン農業漁業食糧省）、ICEX（スペイン貿易庁）、各D.O.P.の規定（中央政府官報掲載やD.O.委員会）などより。\n［ワインのタイプ］ B＝白ワイン R＝赤ワイン Rｓ＝ロゼ Sp＝スパークリングワイン\n\n|  | D.O./D.O.Ca./V.P./V.C. |  | 認定年 | ワインのタイプ | 白ブドウ | 黒ブドウ |\n|---|---|---|---|---|---|---|\n|  | カバ Cava（D.O.） |  | 1986 | Sp | Macabeo, Xarel・lo, Parellada, Malvasía Riojana（Subirat Parent）, Chardonnay |  |\n| 北部地方 |  |  |  |  |  |  |\n| ❶ | リオハ 1Rioja（D.O.Ca.） |  |  |  |  |  |\n| ❷ | 2 | ナバーラ Navarra（D.O.） | 1967 | R, B, Rs, VDL | Viura, Chardonnay, Garnacha Blanca, Malvasía, Moscatel de Grano Menudo, Sauvignon Blanc | Tempranillo, Graciano, Cabernet Sauvignon, Garnacha, Merlot, Mazuelo, Syrah, Pinot Noir |\n|  | パゴ・デ・アリンサノ 🅐 P a g o d e A r ín zano（V.P.） |  | 2009 | R, B | Chardonnay |  |\n|  |  | プラド・デ・イラチェ 🅑 P r a d o d e I ra che（V.P.） | 2009 | R |  | Tempranillo, Merlot, Cabernet Sauvignon, Mazuelo, Graciano, Garnacha |\n|  | パゴ・デ・オタス 🅒 P a g o d e O tazu（V.P.） |  | 2009 | R, B | Chardonnay |  |\n|  |  | フィンカ・ボランディン 🅓 F i n c a B o la n d i n（V.P.） | 2022 | R, B | Chardonnay, Sauvignon Blanc, Moscatel de Grano Menudo | Tempranillo, Cabernet Sauvignon, Merlot, Syrah |\n| ❸ | カンポ・デ・ボルハ 3Campo de Borja（D.O.） |  | 1980 | R, B, Rs, Sp, VND, VDL | Macabeo, Moscatel de Alejandría, Moscatel de Grano Menudo, Chardonnay, Garnacha Blanca, Sauvignon Blanc, Verdejo, Viognier |  |\n|  | 4 | カリニェナ Cariñena（D.O.） | 1960 | R, B, Rs, VND, VDL, Sp | Viura（Macabeo）, Garnacha Blanca, Parellada, Moscatel de Alejandría, Chardonnay, Sauvignon Blanc, Verdejo | Garnacha, Tempranillo, Cariñena, Monastrell, Cabernet Sauvignon, Merlot, Syrah, Juan Ibañez, Vidadillo |\n|  | パゴ・アイレス 🅔 P a g o A y lé（s V.P.） |  | 2011 | R, Rs |  |  |\n|  | 5 | カラタユド Calatayud（D.O.） | 1990 | R, B, Rs, VND, VDL, Sp | Macabeo, Malvasía, Chardonnay, Garnacha Blanca, Moscatel de Alejandría, Gewürztraminer, Sauvignon Blanc | Garnacha Tinta, Mazuelo, Tempranillo, Merlot, Cabernet Sauvignon, Syrah, Monastrell, Bobal |\n|  |  |  | ［特記事項］ Calatayud Superior表示ワインは樹齢50年以上のガルナッチャを最低85％使用義務。 |  |  |  |\n|  | ソモンターノ 6Somontano（D.O.） |  | 1985 | R, B, Rs, VND, VDL, Sp | Macabeo, Garnacha Blanca, Alcañón, Chardonnay, Sauvignon Blanc, Gewürztraminer, Riesling |  |\n| ❹ | 7 | チャコリ・デ・ゲタリア Chacolí de Getaria/ ゲタリアコ・チャコリーナ Getariako Txakolina（D.O.） | 1990 | B, R, Rs | Hondarrabi Zuri, Hondarrabi Zuri Zerratia （Petit Courbu）, Izkiriota（Gros Manseng）, Riesling, Chardonnay | Hondarrabi Beltza |\n|  | チャコリ・デ・ビスカイヤ 8Chacolí de Bizkaia/ ビスカイコ・チャコリーナ Bizkaiko Txakolina（D.O.） |  | 1994 | B, R, Rs | Hondarrabi Zuri, Hondarrabi Zuri Zerratia, Izkiriota, Izkiriota Ttippia（Petit Manseng）, Mune Mahatsa（Folle Blanche）Sauvignon Blanc, Riesling, Chardonnay |  |\n|  | 9 | チャコリ・デ・アラバ Chacolí de Álava/ アラバコ・チャコリーナ Arabako Txakolina（D.O.） | 2002 | B, R, Rs | Hondarrabi Zuri, Izkiriota Ttippia, Hondarrabi Zuri Zerratia, Izkiriota, Sauvignon Blanc, Riesling, Chardonnay | Hondarrabi Beltza |\n| 大西洋地方 |  |  |  |  |  |  |\n| ❺ | リアス・バイシャス Rías Baixa（s D.O.） |  |  |  |  |  |\n|  |  | バルデオラス Valdeorra（s D.O.） | 1957 | B, R, Sp, Tostado | Godello, Palomino, Loureira, Treixadura, Lado, Doña Blanca, Albariño, Torrontés | Mencía, Garnacha Tintorera, Gran Negro, Merenzao, Tempranillo Sousón, Brancellao, Mouratón（Negreda）, Caiño Tinto, Espadeiro, Ferrón |\n|  |  |  | ［特記事項］ ラベル上にGodelloを表示する場合この品種100％、Mencíaを表示する場合はこの品種を85％以上使用義務。 |  |  |  |", "chars": 3370}, {"page": 2, "text": "D.O./D.O.Ca./V.P./V.C. 認定年ワインのタイプ白ブドウ黒ブドウ\nリベイラ・サクラ Mencía, Brancellao, Merenzao, Sousón,\nRibeira Sacra（D.O.） Loureira, Treixadura, Godello, Doña Blanca,\nCaíño Tinto, Garnacha Tintorera, Mouratón\n1997 B, R, Rs Albariño, Branco Lexitimo, Caiño Blanco,\n\n|  | D.O./D.O.Ca./V.P./V.C. |  | 認定年 | ワインのタイプ | 白ブドウ | 黒ブドウ |\n|---|---|---|---|---|---|---|\n|  | リベイラ・サクラ Ribeira Sacra（D.O.） |  |  |  |  |  |\n|  |  | モンテレイ Monterre（i D.O.） | 1996 | B, R | Doña Blanca, Godello, Treixadura, Albariño, Caiño Blanco, Loureira Blanca, Branca de Monterrei | Mencía,, Araúxa（Tempranillo）, Merenzao, Caiño Tinto, Sousón |\n|  | リベイロ Ribeiro（D.O.） |  | 1957 | B, R, Sp, Tostado | Treixadura, Albariño, Godello, Torrontés, Loureira, Lado, Palomino, Caiño Blanco, Albillo |  |\n|  |  | カンガス Canga（s V.C.） | 2004 | B, R | Albarín blanco, Albillo Mayor, Moscatel de Grano Menudo, Godello, Picapoll Blanco, Gewürztraminer | Ｃarrasquín, Verdejo negro, Albarin Tinto, Mencía, Garnacha Tintorera, Merlot, Pinot Noir, Syrah |\n| 地中海地方 |  |  |  |  |  |  |\n| ❻ | プリオラート Priorato（D.O.Ca.） |  | 2009 （D.O.認定は1954年） | B, R, Rs, VDN, VDL, VND | Garnacha Blanca, Macabeo, Pedro Ximénez, Chenin Blanc, Moscatel de Alejandría, Moscatel de Grano Menudo, Xarel・lo, Picapoll Blanco, Viognier |  |\n|  |  | ペネデス Penedé（s D.O.） | 1960 | B, R, Rs, Sp, VDN, VDL, VND | Macabeo, Xarel・lo, Parellada, Subirat Parent, Chardonnay, Chenin Blanc, Moscatel de Alejandría, Malvasía de Sitges, Riesling, Sauvignon Blanc, Moscatel de Grano Menudo, Garnacha Blanca, Gewürztraminer, Sumoll Blanc, Viognier, Xarel・lo Rosado, Forcada | Tempranillo, Cabernet Sauvignon, Garnacha Tinta, Monastrell, Samsó, Merlot, Cabernet Franc, Pinot Noir, Syrah, Sumoll, Petit Verdot, Moneu |\n|  | モンサン Montsan（t D.O.） |  | 2002 | B, R, Rs, VDN, VDL, VND | Chardonnay, Garnacha Blanca, Macabeo, Moscatel de Grano Menudo, Pansal, Parellada, Garnacha Gris, Picapoll Blanco |  |\n|  |  | コステルス・デル・セグレ Costers del Segre（D.O.） | 1988 | B, R, Rs, Sp, VDL | Macabeo, Parellada, Xarel・lo, Chardonnay, Garnacha Blanca, Riesling, Sauvignon Blanc, Albariño, Moscatel de Alejandría, Malvasía, Gewürztraminer, Moscatel de Grano Menudo, Viognier, Chenin Blanc, Godello, Verdejo | Garnacha Tinta, Ull de Llebre（Tempranillo）, Cabernet Sauvignon, Merlot, Monastrell, Trepat, Samsó, Pinot Noir, Syrah, Petit Verdot, Cabernet Franc, Garnacha Tintorera, Malbec |\n|  | コンカ・デ・バルベラ Conca de Barberà（D.O.） |  | 1989 | B, R, Rs, Sp, VDN, VDL | Macabeo, Parellada, Chardonnay, Sauvignon Blanc, Chenin Blanc, Garnacha Blanca, Moscatel de Alejandría, Moscatel de Grano Menudo, Sumoll Blanc, Viognier |  |\n|  |  | テラ・アルタ Terra Alta（D.O.） | 1985 | B, R, Rs, Sp, VDN, VDL | Garnacha Blanca, Macabeo, Parellada, Moscatel de Alejandría, Chardonnay, Chenin Blanc, Pedro Ximénez, Sauvignon Blanc, Frontignan（Moscatel de Grano Menudo）, Viognier | Garnacha Tinta, Garnacha Peluda, Garnacha Tintorera, Cariñena, Ull de llebre, Syrah, Cabernet Sauvignon, Cabernet Franc, Merlot, Morenillo |\n|  | エンポルダ Empordà（D.O.） |  | 1975 | B, R, Rs, Sp, VDN, VDL | Macabeo, Garnacha Blanca, Garnacha Roja, Moscatel de Alejandría, Moscatel de Grano Menudo, Gewürztraminer, Chardonnay, Xarel・lo, Malvasía, Picapoll Blanc, Sauvignon Blanc |  |\n|  |  | アレーリャ Alella（D.O.） | 1956 | B, R, Rs, Sp, VDN, VDL | Garnacha Blanca, Picapoll, Malvasía, Parellada, Macabeo, Chenin Blanc, Pansa Blanca, Chardonnay, Moscatel de Grano Menudo, Sauvignon Blanc | Garnacha, Ull de Llebre, Merlot, Garnacha Peluda, Cabernet Sauvignon, Sumoll, Samsó, Monastrell, Pinot Noir, Syrah |\n|  | タラゴナ Tarragona（D.O.） |  | 1947 | B, R, Rs, Sp, VDL | Macabeo, Parellada, Xarel・lo, Chardonnay, Malvasía, Moscatel de Grano Menudo, Moscatel de Alejandría, Garnacha Blanca, Vynater, Sauvignon Blanc, Malvasía de Sitges, Xarel・lo Rosado, Sumoll Blanc |  |\n|  |  | プラ・デ・バジェス Pla de Bage（s D.O.） | 1997 | B, R, Rs, Sp, VDN, VDL, VND | Macabeo, Parellada, Picapoll, Chardonnay, Gewürztraminer, Sauvignon Blanc, Malvasía de Sitges | Garnacha, Tempranillo, Merlot, Cabernet Sauvignon, Cabernet Franc, Syrah, Sumoll, Samsó, Garró, Picapoll Negro |\n|  | カタルーニャ Cataluña/Catalunya（D.O.） |  | 2001 | B, R, Rs, VDL, Sp | Chardonnay, Garnacha Blanca, Macabeo （Viura）, Moscatel de Alejandría, Frontignan （Moscatel de Grano Menudo）, Parellada, Riesling, Sauvignon Blanc, Gewürztraminer, Malvasía（Subirat Parent）, Malvasía de Sitges, Pedro Ximénez, Picapoll Blanco, Albariño, Sumoll Blanc, Xarel・lo（Pansà Rosada）, Chenin Blanc, Vinyater, Viognier |  |", "chars": 4466}, {"page": 3, "text": "D.O./D.O.Ca./V.P./V.C. 認定年ワインのタイプ白ブドウ黒ブドウ\nバレンシア Macabeo, Malvasía, Merseguera, Moscatel\n❼ Valencia（D.O.） Garnacha, Monastrell, Tempranillo,\nde Alejandría, Pedro Ximénez, Planta Fina de\nTintorera, Cabernet Sauvignon, Merlot,\n\n|  | D.O./D.O.Ca./V.P./V.C. |  | 認定年 | ワインのタイプ | 白ブドウ | 黒ブドウ |\n|---|---|---|---|---|---|---|\n| ❼ |  | バレンシア Valencia（D.O.） | 1957 | B, R, Rs, Sp, VDL | Macabeo, Malvasía, Merseguera, Moscatel de Alejandría, Pedro Ximénez, Planta Fina de Pedralba, Chardonnay, Planta Nova, Tortosí, Verdil, Sémillon, Verdejo, Gewürztraminer, Moscatel de Grano Menudo, Riesling, Sauvignon Blanc, Viognier, Albariño, Garnacha Blanca | Garnacha, Monastrell, Tempranillo, Tintorera, Cabernet Sauvignon, Merlot, Forcayat, Bobal, Bonicaire, Mazuelo, Pinot Noir, Cabernet Franc, Graciano, Malbec, Mencía, Petit Verdot, Syrah, Mandó, Marselán, Miguel de Arco |\n|  | アリカンテ Alicante（D.O.） |  | 1957 | B, R, Rs, Sp, VDL | Airén, Macabeo, Moscatel de Alejandría, Merseguera, Planta Fina, Chardonnay, Verdil, Sauvignon Blanc, Malvasía, Moscatel de Grano Menudo, Viognier, Verdejo, Garnacha Blanca, そのほかの伝統的品種 |  |\n|  |  | ウティエル・レケーナ Utiel-Requena（D.O.） | 1957 | B, R, Rs, Sp, VDL | Macabeo, Merseguera, Chardonnay, Sauvignon Blanc, Tardana（Planta Nova）, Parellada, Verdejo, Moscatel de Grano Menudo, Viognier, Xarel･lo, Godello, Garnacha Blanca, Tortosí, Albariño | Bobal, Tempranillo, Garnacha, Cabernet Sauvignon, Merlot, Syrah, Pinot Noir, Petit Verdot, Garnacha Tintorera, Cabernet Franc, Graciano, Monastrell |\n|  | ロス・バラゲセス 🅕 L o s Ba l a gu ese（s V.P.） |  | 2011 | B, R | Sauvignon Blanc, Chardonnay |  |\n|  |  | エル・テレラソ 🅖 E l T e r re r azo（V.P.） | 2011 | R |  | Bobal, Tempranillo, Syrah, Cabernet Sauvignon, Merlot, Garnacha |\n|  | ベラ・デ・エステナス 🅗 V e r a d e E st e na（s V.P.） |  | 2019 | B, R, Rs | Chardonnay |  |\n|  |  | チョサス・カラスカル 🅘 C h oz a s C a r ra sca（l V.P.） | 2020 | B, R, Rs | Sauvignon Blanc, Chardonnay, Macabeo | Bobal, Garnacha, Tempranillo, Monastrell, Cabernet Sauvignon, Merlot, Syrah, Cabernet Franc |\n| ❽ | ブーリャス Bulla（s D.O.） |  | 1994 | B, R, Rs, Sp, VDL | Macabeo, Airén, Chardonnay, Malvasía, Moscatel de Alejandría, Moscatel de Grano Menudo, Sauvignon Blanc |  |\n|  |  | イェクラ Yecla（D.O.） | 1975 | B, R, Rs ,Sp, VDL | Airén, Merseguera, Macabeo, Malvasía, Chardonnay, Moscatel de Grano Menudo, Sauvignon Blanc, Verdejo | Monastrell, Garnacha Tinta, Garnacha Tintorera, Tempranillo, Merlot, Cabernet Sauvignon, Syrah, Petit Verdot |\n|  | フミーリャ Jumilla（D.O.） |  |  |  |  |  |\n| 内陸部地方 |  |  |  |  |  |  |\n| ❾ | リベラ・デル・ドゥエロ Ribera del Duero（D.O.） |  |  |  |  |  |\n|  |  | シガレス Cigale（s D.O.） | 1991 | B, R, Rs, Sp, VND | Albillo Mayor, Verdejo, Viura, Sauvignon Blanc | Tempranillo（Tinta del País）, Garnacha Tinta, Garnacha Gris, Syrah, Merlot, Cabernet Sauvignon |\n|  | ルエダ Rueda（D.O.） |  |  |  |  |  |\n|  |  | トロ Toro（D.O.） | 1987 | B, R, Rs | Malvasía Castellana（Doña Blanca）, Verdejo | Tinta de Toro（Tempranillo）, Garnacha Tinta |\n|  | ビエルソ Bierzo（D.O.） |  | 1989 | B, R, Rs | Godello, Doña Blanca, Malvasía, Palomino |  |\n|  |  | レオン León（D.O.） | 2008 | B, R, Rs, VND | Verdejo, Albarín Blanco, Godello | Mencía, Prieto Picudo, Tempranillo, Garnacha, Negro Sauri |\n|  | アルランサ Arlanza（D.O.） |  | 2008 | B, R, Rs | Albillo Mayor, Viura |  |\n|  |  | ティエラ・デル・ビノ・デ・サモラ Tierra del Vino de Zamora （D.O.） | 2008 | B, R, Rs | Malvasía, Moscatel de Grano Menudo, Verdejo, Albillo Mayor, Palomino, Godello | Tempranillo, Garnacha, Cabernet Sauvignon |\n|  | アリベス Arribe（s D.O.） |  | 2008 | B, R, Rs | Verdejo, Albillo Mayor, Albillo Real, Malvasía Castellana（Dona Blanca）, Puesta en Cruz |  |\n|  |  | デエサ・ペニャルバ 🅙 D e h e s a P e ña lba（V.P.） | 2022 | R |  | Tempranillo, Cabernet Sauvignon, Merlot, Syrah |\n|  | アバディア・デ・レトゥエルタ 🅚 A b a d ía d e R e t u e rt a（V.P.） |  | 2022 | B, R | Sauvignon Blanc, Gewürztraminer, Riesling ,Godello, Verdejo, Albillo Mayor |  |", "chars": 3879}, {"page": 4, "text": "D.O./D.O.Ca./V.P./V.C. 認定年ワインのタイプ白ブドウ黒ブドウ\n🅛 U ウ r ル u エ e ー ña（ ニャ V.P.） 2021 R, Rs Tempranillo, Cabernet Sauvignon, Merlot,\nシエラ・デ・サラマンカ Viura, Moscatel de Grano Menudo,\nSierra de Salamanca（V.C.） 2011 B, R, Rs Rufete, Garnacha Tinta, Tempranillo\n\n|  | D.O./D.O.Ca./V.P./V.C. |  | 認定年 | ワインのタイプ | 白ブドウ | 黒ブドウ |\n|---|---|---|---|---|---|---|\n|  |  | ウルエーニャ 🅛 U r u e ña（ V.P.） | 2021 | R, Rs |  | Tempranillo, Cabernet Sauvignon, Merlot, Syrah |\n|  | シエラ・デ・サラマンカ Sierra de Salamanca（V.C.） |  | 2011 | B, R, Rs | Viura, Moscatel de Grano Menudo, Palomino, Rufete Serrano Blanco |  |\n|  |  | バリェス・デ・ベナベンテ Valles de Benavente（V.C.） | 2004 | B, R, Rs | Verdejo, Malvasía Castellana | Tempranillo, Prieto Picudo, Mencía, Garnacha, Cabernet Sauvignon |\n|  | バルティエンダス Valtienda（s V.C.） |  | 2009 | R, Rs | Albillo Mayor |  |\n|  |  | セブレロス Cebrero（s V.C.） | 2019 | B, R, Rs | Albillo Real | Garnacha, Garnacha Tintorera, Tempranillo |\n| ❿ | ビノス・デ・マドリード Vinos de Madrid（D.O.） |  | 1990 | B, R, Rs, Sp | Malvar, Airén, Albillo Real, Viura, Parellada, Torrontés, Moscatel de Grano Menudo, Sauvignon Blanc |  |\n| ⓫ |  | ラ・マンチャ La Mancha（D.O.） | 1966 | B, R, Rs, Sp, VND | Airén, Viura（Macabeo）, Chardonnay, Sauvignon Blanc, Moscatel de Grano Menudo, Verdejo, Riesling, Parellada, Viognier, Pedro Ximénez, Torrontés, Gewürztraminer, Moscatel de Alejandría | Cencibe（l Tempranillo）, Garnacha, Moravia Dulce, Cabernet Sauvignon, Merlot, Syrah, Petit Verdot, Monastrell, Bobal, Graciano, Cabernet Franc, Malbec, Pinot Noir, Mencía, Garnacha Tintorera |\n|  | カンポ・デ・ラ・グアルディア 🅜 Ca m p o d e L a G u ar d ia（V.P.） |  | 2009 | B, R | Chardonnay |  |\n|  |  | カサ・デル・ブランコ 🅝 C a s a d e l B l a nco（V.P.） | 2010 | B, R | Sauvignon Blanc, Chardonnay | Tempranillo, Cabernet Sauvignon, Merlot, Syrah, Petit Verdot, Malbec, Cabernet Franc |\n|  | デエサ・デル・カリサル 🅞 D e h e s a d e l C a rriza（l V.P.） |  | 2007 | B, R | Chardonnay |  |\n|  |  | ドミニオ・デ・バルデプーサ 🅟 Do m i n io de V a ld e pu sa（V.P.） | 2003 | R |  | Syrah, Cabernet Sauvignon, Petit Verdot, Merlot, Graciano |\n|  | フィンカ・エレス 🅠 F i n c a É le z（ V.P.） |  | 2007 | B, R | Chardonnay |  |\n|  |  | ギホソ 🅡 G u i joso（V.P.） | 2005 | B, R | Chardonnay, Sauvignon Blanc | Cabernet Sauvignon, Merlot, Syrah, Tempranillo |\n|  | カルサディーリャ 🅢 C a l za d i lla （ V.P.） |  | 2011 | R |  |  |\n|  |  | パゴ・フロレンティーノ 🅣 P a g o F lo re n t in o（V.P.） | 2009 | R |  | Tempranillo, Syrah, Petit Verdot |\n|  | エル・ビカリオ 🅤 E l V i c ar io （V.P.） |  | 2019 | B, R, Rs, VND | Sauvignon Blanc, Chardonnay |  |\n|  |  | ロス・セリーリョス 🅥 L o s C er r il lo （s V.P.） | 2019 | R |  | Tempranillo, Cabernet Sauvignon, Syrah, Petit Verdot |\n|  | バリェガルシア 🅦 V a l le g a rc ía（V.P.） |  | 2019 | B, R | Viognier |  |\n|  |  | ラ・ハラバ 🅧 L a Ja r aba（V.P.） | 2019 | R |  | Tempranillo, Cabernet Sauvignon, Merlot, Graciano |\n|  | ロサレホ 🅨 R o s a lejo（V.P.） |  | 2024 | R |  |  |\n|  |  | バルデペーニャス Valdepeña（s D.O.） | 1968 | B, R, Rs, Sp, VND | Airén, Macabeo, Chardonnay, Verdejo, Sauvignon Blanc, Moscatel de Grano Menudo | Cencibel, Cabernet Sauvignon, Garnacha, Merlot, Syrah, Petit Verdot |\n|  | メントリダ Méntrida（D.O.） |  | 1966 | B, R, Rs, Sp, VDN, VND | Albillo Real, Macabeo, Sauvignon Blanc, Chardonnay, Verdejo, Moscatel de Grano Menudo, Garnacha Blanca |  |\n|  |  | モンデーハル Mondéja（r D.O.） | 1997 | B, R, Rs, VND | Macabeo, Malvar, Torrontés, Moscatel de Grano Menudo, Verdejo, Sauvignon Blanc, Airén | Cabernet Sauvignon, Tempranillo, Syrah, Merlot |\n|  | ウクレス Uclé（s D.O.） |  | 2006 | B, R, Rs, Sp, VND | Verdejo, Chardonnay, Moscatel de Grano Menudo, Sauvignon Blanc, Macabeo |  |\n|  |  | マンチュエラ Manchuela（D.O.） | 2004 | B, R, Rs, Sp, VND, VDN | Albillo Real, Chardonnay, Macabeo, Sauvignon Blanc, Verdejo, Pardillo, Viognier, Moscatel de Grano Menudo, Moscatel de Alejandría, Tardana, Garnacha Blanca | Bobal, Cabernet Sauvignon, Tempranillo, Garnacha, Merlot, Monastrell, Moravia Dulce, Syrah, Garnacha Tintorera, Moravia Agria, Mazuelo, Graciano, Tinto Valesco, Petit Verdot, Cabernet Franc, Pinot Noir, Malbec, Rojal, Touriga Nacional |\n|  | リベラ・デル・フーカル Ribera del Júca（r D.O.） |  | 2003 | B, R, Rs, VND | Moscatel de Grano Menudo, Sauvignon Blanc, Airén, Macabeo, Verdejo, Pardillo, Chardonnay |  |\n|  |  | アルマンサ Almansa（D.O.） | 1966 | B, R, Rs, Sp, VDN, VND | Verdejo, Chardonnay, Sauvignon Blanc, Moscatel Grano Menudo, Macabeo | Monastrell, Garnacha Tintorera, Cabernet Sauvignon, Merlot, Syrah, Garnacha Tinta, Petit Verdot, Tempranillo, Pinot Noir, Cabernet Franc |", "chars": 4457}, {"page": 5, "text": "D.O./D.O.Ca./V.P./V.C. 認定年ワインのタイプ白ブドウ黒ブドウ\nカンポ・デ・カラトラバ Airén, Macabeo, Verdejo, Chardonnay,\nCampo de Calatrava（D.O.） Tempranillo, Cabernet Sauvignon, Merlot,\nMoscatel de Grano Menudo, Sauvignon\n2024 B, R, Rs, Sp Syrah, Bobal, Petit Verdot, Cabernet Franc,\n\n|  | D.O./D.O.Ca./V.P./V.C. |  | 認定年 | ワインのタイプ | 白ブドウ | 黒ブドウ |\n|---|---|---|---|---|---|---|\n|  | カンポ・デ・カラトラバ Campo de Calatrava（D.O.） |  | 2024 | B, R, Rs, Sp | Airén, Macabeo, Verdejo, Chardonnay, Moscatel de Grano Menudo, Sauvignon Blanc, Riesling, Moscatel de Alejandría, Viognier, Gewürztraminer, Albariño |  |\n| ⓬ |  | リベラ・デル・グアディアーナ Ribera del Guadiana（D.O.） | 1999 | B, R, Rs, Sp, VDN | Alarije, Borba, Cayetana Blanca, Pardina, Viura, Chardonnay, Chelva（Montúa）, Eva （Beba de los Santos）, Malvar, Parellada, Pedro Ximénez, Verdejo, Cigüente, Moscatel de Alejandría, Moscatel de Grano Menudo, Perruno, Sauvignon Blanc, Colombard, Xarel･lo, ポルトガル系品種 | Garnacha Tinta, Tempranillo, Bobal, Cabernet Sauvignon, Graciano, Mazuelo, Merlot, Monastrell, Syrah, Garnacha Tintorera, Jaén Tinto, Pinot Noir, Petit Verdot, Malbec, ポルトガル系品種 |\n| 南部地方 |  |  |  |  |  |  |\n| ⓭ | コンダード・デ・ウエルバ Condado de Huelva（D.O.） |  | 1963 | B, R, Rs, VDL, Ge | Zalema, Palomino Fino, Listán del Condado, Garrido Fino, Moscatel de Alejandría, Pedro Ximénez, Chardonnay, Colombard, Sauvignon Blanc, Moscatel de Grano Menudo, Verdejo |  |\n|  |  | ヘレス・ケレス・シェリー・イ Jerez-Xérès-Sherry y（D.O.） マンサニーリャ・サンルーカル・デ・バラメーダ Manzanilla-Sanlúcar de Barrameda（D.O.） | 1935 | Ge, VGL, VDN | Palomino, Moscatel, Pedro Ximénez, Palomino Fino（Listán Blanco）, Beba, Perruno, Vigiriega |  |\n|  | マラガ Málaga（D.O.） |  | 1937 | B, VND, VDN, VDL | Pedro Ximénez, Moscatel de Alejandría, Moscatel Morisco, Lairén, Doradilla |  |\n|  |  | シエラス・デ・マラガ Sierras de Málaga（D.O.） | 2001 | B, R, Rs | Pedro Ximénez, Moscatel de Alejandría, Moscatel de Grano Menudo, Chardonnay, Macabeo, Sauvignon Blanc, Lairén, Doradilla, Colombard, Gewürztraminer, Riesling, Verdejo, Viognier, Garnacha Blanca, Malvasía Aromatica, Montúa, Pardina, Vijariego, Perruno, Vermentino | Romé, Cabernet Sauvignon, Merlot, Syrah, Tempranillo, Garnacha, Cabernet Franc, Pinot Noir, Petit Verdot, Graciano, Malbec, Monastrell, Tintilla, Blauer Limberger, Jaén Tinto, Moscatel Negro, Tinto Valesco |\n|  | モンティーリャ・モリーレス Montilla-Morile（s D.O.） |  | 1945 | B, Ge, VDL, VGL | Pedro Ximénez, Layren, Baladí Verdejo, Moscatel de Grano Menudo, Moscatel de Alejandría, Torrontés, Sauvignon Blanc, Chardonnay, Macabeo |  |\n|  |  | グラナダ Granada（D.O.） | 2018 | B, R, Rs, Sp, VND | Vijiriego, Sauvignon Blanc, Chardonnay, Moscatel de Alejandría, Moscatel de Grano Menudo, Pedro Ximénez, Palomino, Baladí Verdejo, Torrontés, Macabeo, Blanca Gordal, Viognier, Jaén Blanco | Tempranillo, Garnacha Tinta, Cabernet Sauvignon, Cabernet Franc, Merlot, Syrah, Pinot Noir, Monastrell, Romé, Petit Verdot |\n|  | レブリハ Lebrija（V.C.） |  | 2009 | B, R, VDN, VDL, Ge, VGL | Moscatel de Alejandría, Palomino, Palomino Fino, Sauvignon Blanc |  |\n| 諸島 |  |  |  |  |  |  |\n| ⓮ | ビニサレム Binissalem（D.O.） |  |  |  |  |  |\n|  |  | プラ・イ・リェバン Pla i Llevan（t D.O.） | 2001 | B, R, Rs, Sp, VDL | Prensal Blanc, Moscatel de Alejandría, Moscatel de Grano Menudo, Macabeo, Parellada, Chardonnay, Riesling, Giró Ros, Viognier | Callet, Fogoneu, Tempranillo, Manto Negro, Monastrell, Cabernet Sauvignon, Merlot, Syrah, Pinot Noir, Gorgollassa |\n| ⓯ | ランサローテ Lanzarote（D.O.） |  | 1994 | B, R, Rs, Sp, VDL | Burrablanca, Breval, Diego, Listán Blanca, Malvasía, Moscatel de Alejandría, Pedro Ximénez, Albillo Criollo, Gual, Verdello, Torrontés |  |\n|  |  | ラ・パルマ La Palma（D.O.） | 1994 | B, R, Rs, Sp, VND, VDL | Albillo Criollo, Bastardo Blanco, Bermejuela, Burrablanca, Forestera Blanca, Gual, Listán Blanco, Malvasía, Moscatel de Alejandría, Pedro Ximénez, Sabro, Torrontés, Verdello, Doradilla, Diego | Almuñeco（Listán Negro）, Bastardo Negro, Malvasía Rosada, Moscatel Negro, Negramoll, Castellana, Listán Prieto, Tintilla, Vijariego Negro |\n|  | タコロンテ・アセンテホ Tacoronte-Acentejo（D.O.） |  | 1992 | B, R, Rs, Sp, VND, VDL | Gual, Malvasía, Listán Blanco, Marmajuelo, Pedro Ximénez, Verdello, Moscatel de Alejandría, Vijariego, Forastera Blanca, Torrontés, Albillo Criollo, Sabro, Bastardo Blanco, Breval, Burrablanca, Doradilla |  |\n|  |  | バリェ・デ・ラ・オロタバ Valle de la Orotava（D.O.） | 1995 | B, R, Rs, Sp, VDL, VND | Gual, Malvasía, Verdello, Vijariego, Bastardo Blanco, Forastera Blanca, Torrontés, Listán Blanco, Marmajuelo, Moscatel de Alejandría, Pedro Ximénez, Albillo Criollo, Doradilla, Sabro, Breval, Burrablanca | Listán Negro, Malvasía Rosada, Negramoll, Bastardo Negro, Moscatel Negra, Tintilla, Vijariego Negro, Castellana Negra, Cabernet Sauvignon, Listán Prieto, Merlot, Pinot Noir, Syrah, Ruby Cabernet, Tempranillo |", "chars": 4753}, {"page": 6, "text": "D.O./D.O.Ca./V.P./V.C. 認定年ワインのタイプ白ブドウ黒ブドウ\nイコデン・ダウテ・イソーラ Bermejuela, Gual, Malvasía, Moscatel\nYcoden-Daute-Isora（D.O.）\nde Alejandría, Pedro Ximénez, Verdello, Tintilla, Listán Negro, Malvasía Rosada,\nB, R, Rs, Sp,\n\n|  | D.O./D.O.Ca./V.P./V.C. |  | 認定年 | ワインのタイプ | 白ブドウ | 黒ブドウ |\n|---|---|---|---|---|---|---|\n|  | イコデン・ダウテ・イソーラ Ycoden-Daute-Isora（D.O.） |  | 1994 | B, R, Rs, Sp, VDL, VND | Bermejuela, Gual, Malvasía, Moscatel de Alejandría, Pedro Ximénez, Verdello, Vijariego, Bastardo Blanco, Forastera Blanca, Listán Blanco, Sabro, Torrontés, Albillo Criollo, Doradilla |  |\n|  |  | アボナ Abona（D.O.） | 1996 | B, R, Rs, Sp, VDL, VND | Bastardo, Forastera, Listán Blanco, Pedro Ximénez, Verdello, Gual, Bermejuela, Moscatel de Alejandría, Sabro, Albillo Criollo, Malvasía, Torrontés, Doradilla, Vijariego | Bastardo Negro, Malvasía Rosada, Tintilla, Vijariego Negro, Negramoll, Moscatel Negro, Castellana, Cabernet Sauvignon, Listán Negro, Listán Prieto, Merlot, Pinot Noir, Ruby Cabernet, Tempranillo, Syrah |\n|  | バリェ・デ・グイーマル Valle de Güíma（r D.O.） |  | 1996 | B, R, Rs, Sp, VDL, VND | Listán Blanco, Malvasía, Moscatel de Alejandría, Verdello, Vijariego, Gual, Albillo Criollo, Bermejuela, Forastera, Doradilla, Sabro, Burrablanca, Pedro Ximénez, Torrontés |  |\n|  |  | エル・イエロ El Hierro（D.O.） | 1995 | B, R, Rs, Sp, VDL, VND | Vijariego Blanco, Bermejuela, Baboso Blanco, Gual, Malvasía, Pedro Ximénez, Listán Blanco, Moscatel de Alejandría, Burrablanca | Listán Negro, Vijariego Negro, Baboso Negro, Negramoll, Tintilla, Moscatel Negro |\n|  | グラン・カナリア Gran Canaria（D.O.） |  | 2009 | B, R, Rs, Sp, VDL, VND | Gual, Malvasía, Vijariego, Torrontés, Listán Blanco, Marmajuelo, Moscatel de Alejandría, Pedro Ximénez, Albillo Criollo, Breval, Forastera, Doradilla, Verdello, Burrablanca, Bastardo Blanco, Sabro |  |\n|  |  | ラ・ゴメラ La Gomera（D.O.） | 2009 | B, R, Rs, Sp, VND, VDL | Gual,Vijariego, Torrontés, Listán Blanco, Moscatel de Alejandría, Albillo Criollo, Breval, Doradilla, Malvasía, Pedro Ximénez, Sabro, Marmajuelo, Forastera, Verdello | Moscatel Negro, Listán Negro, Negramoll, Tintilla, Malvasía Rosada, Listán Prieto, Cabernet Sauvignon, Merlot, Pinot Noir, Syrah, Castellana, Baboso Negro, Ruby Cabernet, Tempranillo, Vijariego Negro |\n|  | イスラス・カナリアス Islas Canaria（s V.C.） |  | 2011 | B, R, Rs, Sp, VDL, VND | Bermejuela, Doradilla, Forastera Blanca, Malvasía Aromática, Malvasía Volcánica, Moscatel de Alejandría, Sabro, Verdello, Vijariego Blanco, Gual, Baboso Blanco, Breval, Burrablanca, Lístan Blanco, Pedro Ximénez, Torrontés, Albillo Criollo |  |", "chars": 2564}]}